[
	{
		"__metadata": {
			"id": "http://nspad257.pal.sap.corp:8080/com.sap.odata.dynamic.service.provider/odata/costco_03/ConsignmentsSet('PoNumber10')",
			"uri": "http://nspad257.pal.sap.corp:8080/com.sap.odata.dynamic.service.provider/odata/costco_03/ConsignmentsSet('PoNumber10')",
			"type": "payer_direct_srv.Consignments"
		},
		"Company": "001",
		"Currency": "3056700",
		"ExtendedCost": "0.00000000000",
		"InvoiceNumber": "InvoiceNumber10",
		"InvoiceItemNumber": "nvoiceItemNumber10",
		"ItemDescription": "ItemDescription10",
		"PoNumber": "PoNumber10",
		"Quantity": "500.348",
		"QuantityUom": "m10",
		"SalesDate": "/Date(1412924400000)/",
		"TaxCurrency": "ncy10",
		"UnitCost": "0.00000000000",
		"VendorNo": "1234",
		"Warehouse": "se10",
		"Gst": "0.00000000000",
		"Hst": "0.00000000000",
		"Qst": "0.00000000000"
	}
]